binsight_library/__init__.py
binsight_library-0.4.dist-info/METADATA
binsight_library-0.4.dist-info/WHEEL
binsight_library-0.4.dist-info/top_level.txt
binsight_library-0.4.dist-info/RECORD
