Metadata-Version: 2.1
Name: binsight-library
Version: 0.4
Summary: Binsight library for data processing
Home-page: https://github.com/username/my-package
Author: Daniel Blanc
Author-email: dblanc@binsight.app
Classifier: Programming Language :: Python :: 3
Classifier: License :: OSI Approved :: MIT License
Classifier: Operating System :: OS Independent
Requires-Dist: boto3
Requires-Dist: pandas
